jsoncrack_for_sphinx/__init__.py
jsoncrack_for_sphinx/extension.py
jsoncrack_for_sphinx/fixtures.py
jsoncrack_for_sphinx/schema_finder.py
jsoncrack_for_sphinx/config/__init__.py
jsoncrack_for_sphinx/config/config.py
jsoncrack_for_sphinx/config/config_classes.py
jsoncrack_for_sphinx/config/config_main.py
jsoncrack_for_sphinx/config/config_parser.py
jsoncrack_for_sphinx/config/config_parsing.py
jsoncrack_for_sphinx/config/config_utils.py
jsoncrack_for_sphinx/config/config_values.py
jsoncrack_for_sphinx/core/__init__.py
jsoncrack_for_sphinx/core/autodoc.py
jsoncrack_for_sphinx/core/directive.py
jsoncrack_for_sphinx/core/extension.py
jsoncrack_for_sphinx/generators/__init__.py
jsoncrack_for_sphinx/generators/html_generator.py
jsoncrack_for_sphinx/generators/rst_generator.py
jsoncrack_for_sphinx/patterns/__init__.py
jsoncrack_for_sphinx/patterns/custom_patterns.py
jsoncrack_for_sphinx/patterns/pattern_generator.py
jsoncrack_for_sphinx/patterns/pattern_strategies.py
jsoncrack_for_sphinx/patterns/pattern_strategies_impl.py
jsoncrack_for_sphinx/patterns/pattern_utils.py
jsoncrack_for_sphinx/schema/__init__.py
jsoncrack_for_sphinx/schema/schema_finder.py
jsoncrack_for_sphinx/schema/schema_utils.py
jsoncrack_for_sphinx/search/__init__.py
jsoncrack_for_sphinx/search/search_policy.py
jsoncrack_for_sphinx/static/jsoncrack-schema.css
jsoncrack_for_sphinx/static/jsoncrack-sphinx.js
jsoncrack_for_sphinx/utils/__init__.py
jsoncrack_for_sphinx/utils/fixtures.py
jsoncrack_for_sphinx/utils/types.py
jsoncrack_for_sphinx/utils/utils.py
jsoncrack_for_sphinx-0.1.1.dist-info/licenses/LICENSE
jsoncrack_for_sphinx-0.1.1.dist-info/METADATA
jsoncrack_for_sphinx-0.1.1.dist-info/WHEEL
jsoncrack_for_sphinx-0.1.1.dist-info/entry_points.txt
jsoncrack_for_sphinx-0.1.1.dist-info/top_level.txt
jsoncrack_for_sphinx-0.1.1.dist-info/RECORD
