Metadata-Version: 2.4
Name: jsoncrack-for-sphinx
Version: 0.1.1
Summary: Sphinx extension for automatically adding JSON and JSON Schema to documentation
Author: Miskler
License: MIT
Project-URL: Homepage, https://miskler.github.io/jsoncrack-for-sphinx/examples.html
Project-URL: Repository, https://github.com/miskler/jsoncrack-for-sphinx
Project-URL: Issues, https://github.com/miskler/jsoncrack-for-sphinx/issues
Project-URL: Documentation, https://miskler.github.io/jsoncrack-for-sphinx/quickstart
Classifier: Development Status :: 3 - Alpha
Classifier: Intended Audience :: Developers
Classifier: Operating System :: OS Independent
Classifier: Programming Language :: Python :: 3
Classifier: Programming Language :: Python :: 3.8
Classifier: Programming Language :: Python :: 3.9
Classifier: Programming Language :: Python :: 3.10
Classifier: Programming Language :: Python :: 3.11
Classifier: Programming Language :: Python :: 3.12
Classifier: Framework :: Sphinx :: Extension
Classifier: Topic :: Documentation
Classifier: Topic :: Documentation :: Sphinx
Requires-Python: >=3.8
License-File: LICENSE
Requires-Dist: sphinx>=4.0.0
Requires-Dist: jsf>=0.8.0
Provides-Extra: test
Requires-Dist: pytest>=7.0.0; extra == "test"
Requires-Dist: pytest-cov>=4.0.0; extra == "test"
Provides-Extra: dev
Requires-Dist: black>=22.0.0; extra == "dev"
Requires-Dist: isort>=5.0.0; extra == "dev"
Requires-Dist: flake8>=4.0.0; extra == "dev"
Requires-Dist: mypy>=0.900; extra == "dev"
Requires-Dist: types-docutils; extra == "dev"
Dynamic: license-file
